fints_url/__init__.py
fints_url/bank_info.pickle
fints_url/cli.py
fints_url/update_bank_info.py
fints_url-0.7.dist-info/LICENSE
fints_url-0.7.dist-info/METADATA
fints_url-0.7.dist-info/WHEEL
fints_url-0.7.dist-info/entry_points.txt
fints_url-0.7.dist-info/top_level.txt
fints_url-0.7.dist-info/RECORD
