Metadata-Version: 2.1
Name: fints-url
Version: 0.7
Summary: FinTS URL Retriever
Home-page: http://github.com/dr-duplo/python-fints-url
Author: dr-duplo
Author-email: monsieur.cm@gmx.de
License: MIT
Keywords: fints url bank german iban code
Platform: UNKNOWN
Classifier: Development Status :: 3 - Alpha
Classifier: License :: OSI Approved :: MIT License
Classifier: Programming Language :: Python :: 3
Classifier: Topic :: Office/Business :: Financial :: Accounting
Requires-Dist: requests
Requires-Dist: lxml
Requires-Dist: schwifty
Requires-Dist: argparse
